{
  "development": {
    "ENV_TYPE": "dev",
    "EPAYCO_TEST": true,
    "API_URL": "http://localhost:3001",
    "APP_URL": "http://localhost:9000",
    "FRONT_URL": "http://localhost:9001",
    "G_MAP_KEY": "AIzaSyC62qW1RdPQLPCGgL3MwzFjl43mEjk5cd0",
    "EPAYCO_PRIVATE_KEY": "809676747522c1d91089923df983f97e"
  },
  "production": {
    "ENV_TYPE": "prod",
    "EPAYCO_TEST": false,
    "API_URL": "http://18.189.94.179",
    "APP_URL": "http://onex.host",
    "FRONT_URL": "http://catalogo.onex.host",
    "G_MAP_KEY": "AIzaSyC62qW1RdPQLPCGgL3MwzFjl43mEjk5cd0",
    "EPAYCO_PRIVATE_KEY": "809676747522c1d91089923df983f97e"
  },
  "test": {
    "ENV_TYPE": "test",
    "EPAYCO_TEST": false,
    "API_URL": "",
    "APP_URL": "",
    "FRONT_URL": "",
    "G_MAP_KEY": "AIzaSyC62qW1RdPQLPCGgL3MwzFjl43mEjk5cd0",
    "EPAYCO_PRIVATE_KEY": "809676747522c1d91089923df983f97e"
  }
}
